cdk8s_plus_19/__init__.py
cdk8s_plus_19/py.typed
cdk8s_plus_19/_jsii/__init__.py
cdk8s_plus_19/_jsii/cdk8s-plus-19@1.0.0-beta.0.jsii.tgz
cdk8s_plus_19-1.0.0b0.dist-info/LICENSE
cdk8s_plus_19-1.0.0b0.dist-info/METADATA
cdk8s_plus_19-1.0.0b0.dist-info/NOTICE
cdk8s_plus_19-1.0.0b0.dist-info/WHEEL
cdk8s_plus_19-1.0.0b0.dist-info/top_level.txt
cdk8s_plus_19-1.0.0b0.dist-info/RECORD
