Metadata-Version: 2.1
Name: cdk8s-plus-19
Version: 1.0.0b0
Summary: High level abstractions on top of cdk8s
Home-page: https://github.com/cdk8s-team/cdk8s-plus.git
Author: Amazon Web Services
License: Apache-2.0
Project-URL: Source, https://github.com/cdk8s-team/cdk8s-plus.git
Platform: UNKNOWN
Classifier: Intended Audience :: Developers
Classifier: Operating System :: OS Independent
Classifier: Programming Language :: JavaScript
Classifier: Programming Language :: Python :: 3 :: Only
Classifier: Programming Language :: Python :: 3.6
Classifier: Programming Language :: Python :: 3.7
Classifier: Programming Language :: Python :: 3.8
Classifier: Programming Language :: Python :: 3.9
Classifier: Typing :: Typed
Classifier: Development Status :: 5 - Production/Stable
Classifier: License :: OSI Approved
Requires-Python: >=3.6
License-File: LICENSE
License-File: NOTICE
Requires-Dist: cdk8s (==1.0.0.b46)
Requires-Dist: constructs (<4.0.0,>=3.3.147)
Requires-Dist: jsii (<2.0.0,>=1.34.0)
Requires-Dist: publication (>=0.0.3)
